secretkey/__init__.py
secretkey/cli.py
secretkey/secretkey.py
tchappui_secretkey-0.1.0.dist-info/AUTHORS.rst
tchappui_secretkey-0.1.0.dist-info/LICENSE
tchappui_secretkey-0.1.0.dist-info/METADATA
tchappui_secretkey-0.1.0.dist-info/WHEEL
tchappui_secretkey-0.1.0.dist-info/entry_points.txt
tchappui_secretkey-0.1.0.dist-info/top_level.txt
tchappui_secretkey-0.1.0.dist-info/RECORD
