Metadata-Version: 2.1
Name: tchappui-secretkey
Version: 0.1.0
Summary: Tool to generate easily a new secret key to be used in the django or flask webapp.
Home-page: https://github.com/tchappui/secretkey
Author: Thierry Chappuis
Author-email: tchappui@gmail.com
License: MIT license
Keywords: secretkey
Platform: UNKNOWN
Classifier: Development Status :: 2 - Pre-Alpha
Classifier: Intended Audience :: Developers
Classifier: License :: OSI Approved :: MIT License
Classifier: Natural Language :: English
Classifier: Programming Language :: Python :: 3
Classifier: Programming Language :: Python :: 3.5
Classifier: Programming Language :: Python :: 3.6
Classifier: Programming Language :: Python :: 3.7
Classifier: Programming Language :: Python :: 3.8
Requires-Python: >=3.5
Requires-Dist: Click (>=7.0)
